unicorn/__init__.py
unicorn/arm64_const.py
unicorn/arm_const.py
unicorn/m68k_const.py
unicorn/mips_const.py
unicorn/sparc_const.py
unicorn/unicorn.py
unicorn/unicorn_const.py
unicorn/x86_const.py
unicorn/include/unicorn/arm.h
unicorn/include/unicorn/arm64.h
unicorn/include/unicorn/m68k.h
unicorn/include/unicorn/mips.h
unicorn/include/unicorn/platform.h
unicorn/include/unicorn/sparc.h
unicorn/include/unicorn/unicorn.h
unicorn/include/unicorn/x86.h
unicorn/lib/libgcc_s_dw2-1.dll
unicorn/lib/libwinpthread-1.dll
unicorn/lib/unicorn.dll
unicorn/lib/unicorn.lib
unicorn_unipacker-1.0.3b7.dist-info/METADATA
unicorn_unipacker-1.0.3b7.dist-info/WHEEL
unicorn_unipacker-1.0.3b7.dist-info/top_level.txt
unicorn_unipacker-1.0.3b7.dist-info/zip-safe
unicorn_unipacker-1.0.3b7.dist-info/RECORD
