Metadata-Version: 1.1
Name: unicorn-unipacker
Version: 1.0.3b7
Summary: Un{i}packer fork of Unicorn CPU emulator engine
Home-page: https://github.com/unipacker/unicorn
Author: Un{i}packer Team
Author-email: masrepus97@gmail.com
License: UNKNOWN
Platform: UNKNOWN
Classifier: License :: OSI Approved :: BSD License
Classifier: Programming Language :: Python :: 2
Classifier: Programming Language :: Python :: 3
Requires: ctypes
Provides: unicorn
